alibabacloud_eventbridge20200401/__init__.py
alibabacloud_eventbridge20200401/client.py
alibabacloud_eventbridge20200401/models/__init__.py
alibabacloud_eventbridge20200401/models/_bai_lian_agent_transform_parameters.py
alibabacloud_eventbridge20200401/models/_check_service_linked_role_for_product_request.py
alibabacloud_eventbridge20200401/models/_check_service_linked_role_for_product_response.py
alibabacloud_eventbridge20200401/models/_check_service_linked_role_for_product_response_body.py
alibabacloud_eventbridge20200401/models/_create_api_destination_request.py
alibabacloud_eventbridge20200401/models/_create_api_destination_response.py
alibabacloud_eventbridge20200401/models/_create_api_destination_response_body.py
alibabacloud_eventbridge20200401/models/_create_api_destination_shrink_request.py
alibabacloud_eventbridge20200401/models/_create_connection_request.py
alibabacloud_eventbridge20200401/models/_create_connection_response.py
alibabacloud_eventbridge20200401/models/_create_connection_response_body.py
alibabacloud_eventbridge20200401/models/_create_connection_shrink_request.py
alibabacloud_eventbridge20200401/models/_create_event_bus_request.py
alibabacloud_eventbridge20200401/models/_create_event_bus_response.py
alibabacloud_eventbridge20200401/models/_create_event_bus_response_body.py
alibabacloud_eventbridge20200401/models/_create_event_source_request.py
alibabacloud_eventbridge20200401/models/_create_event_source_response.py
alibabacloud_eventbridge20200401/models/_create_event_source_response_body.py
alibabacloud_eventbridge20200401/models/_create_event_source_shrink_request.py
alibabacloud_eventbridge20200401/models/_create_event_streaming_request.py
alibabacloud_eventbridge20200401/models/_create_event_streaming_response.py
alibabacloud_eventbridge20200401/models/_create_event_streaming_response_body.py
alibabacloud_eventbridge20200401/models/_create_event_streaming_shrink_request.py
alibabacloud_eventbridge20200401/models/_create_rule_request.py
alibabacloud_eventbridge20200401-8.0.3.dist-info/LICENSE
alibabacloud_eventbridge20200401-8.0.3.dist-info/METADATA
alibabacloud_eventbridge20200401-8.0.3.dist-info/WHEEL
alibabacloud_eventbridge20200401-8.0.3.dist-info/top_level.txt
alibabacloud_eventbridge20200401-8.0.3.dist-info/RECORD
